xontrib_homebrew/__init__.py
xontrib_homebrew/main.py
xontrib_homebrew-0.2.1.dist-info/METADATA
xontrib_homebrew-0.2.1.dist-info/entry_points.txt
xontrib_homebrew-0.2.1.dist-info/WHEEL
xontrib_homebrew-0.2.1.dist-info/RECORD
