Metadata-Version: 2.1
Name: xontrib-homebrew
Version: 0.2.1
Summary: Add Homebrew's shell environment to xonsh on macOS/Linux
Home-page: https://github.com/eugenesvk/xontrib-homebrew
License: MIT
Keywords: xontrib,xonsh
Author: Evgeny
Author-email: es.bugzilla@gmail.com
Requires-Python: >=3.8
Classifier: Intended Audience :: Developers
Classifier: License :: OSI Approved :: MIT License
Classifier: Natural Language :: English
Classifier: Operating System :: OS Independent
Classifier: Programming Language :: Python :: 3
Classifier: Programming Language :: Python :: 3.8
Classifier: Programming Language :: Python :: 3.9
Classifier: Programming Language :: Python :: 3.10
Classifier: Programming Language :: Python :: 3.11
Classifier: Programming Language :: Python :: 3
Classifier: Topic :: System :: Shells
Classifier: Topic :: System :: System Shells
Classifier: Topic :: Terminals
Requires-Dist: xonsh (>=0.12.5)
Project-URL: Code, https://github.com/eugenesvk/xontrib-homebrew
Project-URL: Documentation, https://github.com/eugenesvk/xontrib-homebrew/blob/master/ReadMe.md
Project-URL: Issue tracker, https://github.com/eugenesvk/xontrib-homebrew/issues
Project-URL: Repository, https://github.com/eugenesvk/xontrib-homebrew
